{"entities":{"bf788257-0888-497f-bcd2-15b0c665acbf":{"enabled":true,"tags":[],"children":["59390e51-2886-4bd0-99c0-4ef2702ea189","a1513e69-2aa2-4b1b-9eb4-e4c376cefcc1"],"position":[0,0,0],"rotation":[0,0,0],"scale":[0.018,0.018,0.018],"resource_id":"bf788257-0888-497f-bcd2-15b0c665acbf","name":"RootNode","components":{"anim":{"stateGraphAsset":175987318,"animationAssets":{"Base:Shuffling":{"asset":172490762},"Base:Wave Hip Hop Dance":{"asset":172490759},"Base:XUI":{"asset":172484165},"Base:Idle":{"asset":172639731},"Base:Head Gesture":{"asset":175987237},"Base:Thoughtful Head Shake":{"asset":175987237},"Base:Bored":{"asset":175987237},"Base:Listening To Music":{"asset":175987237},"Base:Happy Idle":{"asset":175987237},"Base:Look Around":{"asset":175987237},"Base:Shrugging":{"asset":175987237},"Base:Waving Gesture":{"asset":175987237},"Base:Sad Idle":{"asset":175987237},"Base:Pointing":{"asset":175987237},"Base:Hip Hop Dancing":{"asset":175987237},"Base:Pointing 2":{"asset":175987237},"Base:Running":{"asset":174026761},"Base:Defeated":{"asset":174027632},"Base:Defeat Head Gesture":{"asset":172491505},"Base:Round Victory":{"asset":180924983},"Base:Button Pushing":{"asset":176165337},"Base:Rumba Dancing":{"asset":175996451},"Base:Victory Idle":{"asset":180924983},"Base:Round Victory Loop 1":{"asset":172491522},"Base:Round Victory Loop 2":{"asset":173062376},"Base:Jump At Button":{"asset":176061578},"Base:Wrecking Ball Hit":{"asset":176166434},"Base:Agony":{"asset":180921209},"Base:Knocked Out":{"asset":180923116},"Base:DC Victory":{"asset":180923879},"Base:DC Round Victory":{"asset":180924983},"Base:Holding Cup":{"asset":180927915},"Base:Waterfall":{"asset":182088564},"Base:Tornado":{"asset":182088850},"Base:Frozen":{"asset":182089005},"Base:Lava":{"asset":182089151},"Base:Walking":{"asset":190089778}},"enabled":true,"speed":1,"activate":true,"playing":false,"rootBone":"a1513e69-2aa2-4b1b-9eb4-e4c376cefcc1","masks":{},"normalizeWeights":false}},"parent":null},"59390e51-2886-4bd0-99c0-4ef2702ea189":{"enabled":true,"tags":[],"children":[],"position":[0,0,0],"rotation":[0,0,0],"scale":[1,1,1],"resource_id":"59390e51-2886-4bd0-99c0-4ef2702ea189","name":"BasicCharacter_3","components":{"render":{"enabled":true,"type":"asset","asset":176752970,"materialAssets":[172562835],"layers":[0],"batchGroupId":null,"castShadows":true,"castShadowsLightmap":true,"receiveShadows":true,"lightmapped":false,"lightmapSizeMultiplier":1,"castShadowsLightMap":true,"lightMapped":false,"lightMapSizeMultiplier":1,"isStatic":false,"rootBone":"a1513e69-2aa2-4b1b-9eb4-e4c376cefcc1"}},"parent":"bf788257-0888-497f-bcd2-15b0c665acbf"},"a1513e69-2aa2-4b1b-9eb4-e4c376cefcc1":{"enabled":true,"tags":[],"children":["728a8f40-3ddb-461c-aba7-c10c086e04d9"],"position":[0,0,0],"rotation":[-90,0,0],"scale":[100,100,100],"resource_id":"a1513e69-2aa2-4b1b-9eb4-e4c376cefcc1","name":"metarig","components":{},"parent":"bf788257-0888-497f-bcd2-15b0c665acbf"},"728a8f40-3ddb-461c-aba7-c10c086e04d9":{"enabled":true,"tags":[],"children":["088b640c-7c8e-41c2-8602-f0c267933147","9388a103-ad25-4a32-8e39-1f037282d1ef","f64f68ec-ad35-4574-8b40-0578cf3c5a69"],"position":[0,0.044859,0.63876],"rotation":[104.121,-0.00000666547,0.0000264953],"scale":[1,1,1],"resource_id":"728a8f40-3ddb-461c-aba7-c10c086e04d9","name":"pelvis","components":{},"parent":"a1513e69-2aa2-4b1b-9eb4-e4c376cefcc1"},"088b640c-7c8e-41c2-8602-f0c267933147":{"enabled":true,"tags":[],"children":["b85d91da-b083-48b5-a6d4-f8e145289dd1"],"position":[2.22045e-15,0.126578,1.76951e-8],"rotation":[-8.95745,-0.000013827,-0.00000212695],"scale":[1,1,1],"resource_id":"088b640c-7c8e-41c2-8602-f0c267933147","name":"spine.001","components":{},"parent":"728a8f40-3ddb-461c-aba7-c10c086e04d9"},"b85d91da-b083-48b5-a6d4-f8e145289dd1":{"enabled":true,"tags":[],"children":["393a10c3-33cb-419b-90f7-54dd13e94351"],"position":[1.77636e-15,0.1517,-5.18048e-9],"rotation":[-6.43555,-8.6092e-8,-0.00000153114],"scale":[1,1,1],"resource_id":"b85d91da-b083-48b5-a6d4-f8e145289dd1","name":"spine.002","components":{},"parent":"088b640c-7c8e-41c2-8602-f0c267933147"},"393a10c3-33cb-419b-90f7-54dd13e94351":{"enabled":true,"tags":[],"children":["fdeab72d-7077-40a5-bcf5-278c0315a799","0e2c14c5-2dc1-4f1f-adf8-a55fb51587d1","f52d55e1-d03a-477f-b83c-edbce8d1811e"],"position":[4.44089e-16,0.201338,-9.31323e-10],"rotation":[-0.00549542,6.96182e-12,-1.31024e-9],"scale":[1,1,1],"resource_id":"393a10c3-33cb-419b-90f7-54dd13e94351","name":"spine.003","components":{},"parent":"b85d91da-b083-48b5-a6d4-f8e145289dd1"},"fdeab72d-7077-40a5-bcf5-278c0315a799":{"enabled":true,"tags":[],"children":["c5ab4b91-7aed-4a9e-99a9-b4544f552538"],"position":[-1.38581e-16,0.200472,0],"rotation":[24.9759,-0.00000127746,0.00000576795],"scale":[1,1,1],"resource_id":"fdeab72d-7077-40a5-bcf5-278c0315a799","name":"neck","components":{},"parent":"393a10c3-33cb-419b-90f7-54dd13e94351"},"c5ab4b91-7aed-4a9e-99a9-b4544f552538":{"enabled":true,"tags":[],"children":[],"position":[6.42922e-15,0.0493354,-2.23517e-8],"rotation":[-22.979,-0.000001084,-0.00000533296],"scale":[1,1,1],"resource_id":"c5ab4b91-7aed-4a9e-99a9-b4544f552538","name":"head","components":{},"parent":"fdeab72d-7077-40a5-bcf5-278c0315a799"},"0e2c14c5-2dc1-4f1f-adf8-a55fb51587d1":{"enabled":true,"tags":[],"children":["c58ec979-352a-4e04-91f5-6dd4b08f0666"],"position":[0.0937934,0.182089,0.0644567],"rotation":[-87.5075,-59.5051,-2.17844],"scale":[1,1,1],"resource_id":"0e2c14c5-2dc1-4f1f-adf8-a55fb51587d1","name":"shoulder.L","components":{},"parent":"393a10c3-33cb-419b-90f7-54dd13e94351"},"c58ec979-352a-4e04-91f5-6dd4b08f0666":{"enabled":true,"tags":[],"children":["5f5e6236-f428-4964-9a98-5e350173023a"],"position":[0.0285399,0.200924,-0.0224123],"rotation":[74.0092,109.985,52.8094],"scale":[1,1,1],"resource_id":"c58ec979-352a-4e04-91f5-6dd4b08f0666","name":"upper_arm.L","components":{},"parent":"0e2c14c5-2dc1-4f1f-adf8-a55fb51587d1"},"5f5e6236-f428-4964-9a98-5e350173023a":{"enabled":true,"tags":[],"children":["85ba52fa-1ab4-4f97-9d3c-94bfdcf415f4"],"position":[-7.82311e-8,0.299302,-7.45058e-9],"rotation":[11.8739,-4.49043,-0.174372],"scale":[1,1,1],"resource_id":"5f5e6236-f428-4964-9a98-5e350173023a","name":"forearm.L","components":{},"parent":"c58ec979-352a-4e04-91f5-6dd4b08f0666"},"85ba52fa-1ab4-4f97-9d3c-94bfdcf415f4":{"enabled":true,"tags":[],"children":[],"position":[-3.81842e-8,0.257812,-7.45058e-9],"rotation":[-0.522594,0.302521,3.08652],"scale":[1,1,1],"resource_id":"85ba52fa-1ab4-4f97-9d3c-94bfdcf415f4","name":"hand.L","components":{},"parent":"5f5e6236-f428-4964-9a98-5e350173023a"},"f52d55e1-d03a-477f-b83c-edbce8d1811e":{"enabled":true,"tags":[],"children":["e1c5f4bc-0740-4a3b-8ae4-2fa30178d82e"],"position":[-0.0937934,0.182089,0.0644566],"rotation":[-87.5074,59.5051,2.17851],"scale":[1,1,1],"resource_id":"f52d55e1-d03a-477f-b83c-edbce8d1811e","name":"shoulder.R","components":{},"parent":"393a10c3-33cb-419b-90f7-54dd13e94351"},"e1c5f4bc-0740-4a3b-8ae4-2fa30178d82e":{"enabled":true,"tags":[],"children":["ce81399a-6b7c-402e-ba53-8e82b3500fbb"],"position":[-0.0285399,0.200924,-0.0224123],"rotation":[74.0091,-109.985,-52.8093],"scale":[1,1,1],"resource_id":"e1c5f4bc-0740-4a3b-8ae4-2fa30178d82e","name":"upper_arm.R","components":{},"parent":"f52d55e1-d03a-477f-b83c-edbce8d1811e"},"ce81399a-6b7c-402e-ba53-8e82b3500fbb":{"enabled":true,"tags":[],"children":["5d3321e3-4b4c-4015-9608-51482632d165"],"position":[-5.89062e-8,0.299302,0],"rotation":[11.8739,4.49041,0.174363],"scale":[1,1,1],"resource_id":"ce81399a-6b7c-402e-ba53-8e82b3500fbb","name":"forearm.R","components":{},"parent":"e1c5f4bc-0740-4a3b-8ae4-2fa30178d82e"},"5d3321e3-4b4c-4015-9608-51482632d165":{"enabled":true,"tags":[],"children":[],"position":[-6.75209e-8,0.257812,-1.86265e-9],"rotation":[-0.522596,-0.302526,-3.08652],"scale":[1,1,1],"resource_id":"5d3321e3-4b4c-4015-9608-51482632d165","name":"hand.R","components":{},"parent":"ce81399a-6b7c-402e-ba53-8e82b3500fbb"},"9388a103-ad25-4a32-8e39-1f037282d1ef":{"enabled":true,"tags":[],"children":["161d6d95-561b-4b28-9447-4a6b9ac16cd8"],"position":[0.197207,-0.000904118,0.0360933],"rotation":[158.336,0.263678,0.148884],"scale":[1,1,1],"resource_id":"9388a103-ad25-4a32-8e39-1f037282d1ef","name":"thigh.L","components":{},"parent":"728a8f40-3ddb-461c-aba7-c10c086e04d9"},"161d6d95-561b-4b28-9447-4a6b9ac16cd8":{"enabled":true,"tags":[],"children":["52028c7e-1e02-480a-a450-cdcf5f3b2de0"],"position":[-1.03537e-8,0.253831,5.76256e-9],"rotation":[17.8235,0.190136,0.235723],"scale":[1,1,1],"resource_id":"161d6d95-561b-4b28-9447-4a6b9ac16cd8","name":"shin.L","components":{},"parent":"9388a103-ad25-4a32-8e39-1f037282d1ef"},"52028c7e-1e02-480a-a450-cdcf5f3b2de0":{"enabled":true,"tags":[],"children":["2f825e93-bafd-4df2-bef1-3025a9ea984c"],"position":[-1.77213e-9,0.204011,-1.15499e-9],"rotation":[-41.2681,-2.74322,-2.87792],"scale":[1,1,1],"resource_id":"52028c7e-1e02-480a-a450-cdcf5f3b2de0","name":"foot.L","components":{},"parent":"161d6d95-561b-4b28-9447-4a6b9ac16cd8"},"2f825e93-bafd-4df2-bef1-3025a9ea984c":{"enabled":true,"tags":[],"children":[],"position":[1.5134e-8,0.173092,-9.31323e-10],"rotation":[58.9373,-179.839,3.97172],"scale":[1,1,1],"resource_id":"2f825e93-bafd-4df2-bef1-3025a9ea984c","name":"toe.L","components":{},"parent":"52028c7e-1e02-480a-a450-cdcf5f3b2de0"},"f64f68ec-ad35-4574-8b40-0578cf3c5a69":{"enabled":true,"tags":[],"children":["947d0ca3-dd4c-467c-ad03-a8764f7522f7"],"position":[-0.197207,-0.000904117,0.0360931],"rotation":[158.336,-0.263724,-0.14889],"scale":[1,1,1],"resource_id":"f64f68ec-ad35-4574-8b40-0578cf3c5a69","name":"thigh.R","components":{},"parent":"728a8f40-3ddb-461c-aba7-c10c086e04d9"},"947d0ca3-dd4c-467c-ad03-a8764f7522f7":{"enabled":true,"tags":[],"children":["f40581b9-3a4a-40e9-b29a-3f9e9bdb1dd9"],"position":[-1.3024e-9,0.253831,8.20728e-9],"rotation":[17.8235,-0.190131,-0.235725],"scale":[1,1,1],"resource_id":"947d0ca3-dd4c-467c-ad03-a8764f7522f7","name":"shin.R","components":{},"parent":"f64f68ec-ad35-4574-8b40-0578cf3c5a69"},"f40581b9-3a4a-40e9-b29a-3f9e9bdb1dd9":{"enabled":true,"tags":[],"children":["ca9a4fe7-b627-4470-abbc-3f59b35e8bcf"],"position":[2.01153e-8,0.204011,-2.0075e-10],"rotation":[-41.2681,2.74322,2.87793],"scale":[1,1,1],"resource_id":"f40581b9-3a4a-40e9-b29a-3f9e9bdb1dd9","name":"foot.R","components":{},"parent":"947d0ca3-dd4c-467c-ad03-a8764f7522f7"},"ca9a4fe7-b627-4470-abbc-3f59b35e8bcf":{"enabled":true,"tags":[],"children":[],"position":[-2.79397e-9,0.173092,2.32831e-9],"rotation":[58.9374,179.839,-3.97166],"scale":[1,1,1],"resource_id":"ca9a4fe7-b627-4470-abbc-3f59b35e8bcf","name":"toe.R","components":{},"parent":"f40581b9-3a4a-40e9-b29a-3f9e9bdb1dd9"}}}